MANIFEST.in
README.md
setup.cfg
setup.py
anamic/__init__.py
anamic/fitter.py
anamic/geometry.py
anamic.egg-info/PKG-INFO
anamic.egg-info/SOURCES.txt
anamic.egg-info/dependency_links.txt
anamic.egg-info/top_level.txt
anamic/data/mt_structure.csv
anamic/imaging/__init__.py
anamic/imaging/color.py
anamic/imaging/dimensions.py
anamic/imaging/features.py
anamic/imaging/metadata.py
anamic/simulator/__init__.py
anamic/simulator/fov.py
anamic/simulator/mt_simulator.py
anamic/simulator/structure.py
anamic/utils/__init__.py
anamic/utils/css.py
anamic/utils/parallel.py
anamic/viz/__init__.py
anamic/viz/drawer.py
anamic/viz/log_widget.py
anamic/viz/plot.py
anamic/viz/plot_3d.py
anamic/viz/viewer.py