Metadata-Version: 1.1
Name: anamic
Version: 0.2.3
Summary: Simulate, fit and analyze microtubules.
Home-page: https://github.com/hadim/anamic/
Author: Hadrien Mary
Author-email: hadrien.mary@gmail.com
License: UNKNOWN
Platform: UNKNOWN
Classifier: Development Status :: 5 - Production/Stable
Classifier: Natural Language :: English
Classifier: License :: OSI Approved :: BSD License
Classifier: Operating System :: OS Independent
Classifier: Programming Language :: Python
Classifier: Programming Language :: Python :: 3
